datatile/__init__.py
datatile/pkg.py
datatile/catalog/__init__.py
datatile/summary/__init__.py
datatile/summary/df.py
datatile/viz/__init__.py
datatile-1.0.2.dist-info/METADATA
datatile-1.0.2.dist-info/WHEEL
datatile-1.0.2.dist-info/top_level.txt
datatile-1.0.2.dist-info/RECORD
